nb_utils/__init__.py
nb_utils/basic_file_folder_creation.py
nb_utils/database.py
nb_utils/datatype_manipulation.py
nb_utils/datetime_utilities.py
nb_utils/dict_manipulation.py
nb_utils/dump.py
nb_utils/error_handling.py
nb_utils/face.py
nb_utils/file_dir_handling.py
nb_utils/image_conversion.py
nb_utils/image_manip.py
nb_utils/list_manipulation.py
nb_utils/network.py
nb_utils/requirements.txt
nb_utils/response_writer.py
nb_utils/selenium_utils.py
nb_utils/text_processing.py
nb_utils-0.1.1.dist-info/LICENSE
nb_utils-0.1.1.dist-info/WHEEL
nb_utils-0.1.1.dist-info/METADATA
nb_utils-0.1.1.dist-info/RECORD
