Metadata-Version: 2.1
Name: nb-utils
Version: 0.1.1
Summary: Python utilities
Author: Nivratti
Author-email: boyanenivratti@gmail.com
Requires-Python: >=3.2,<4.0
Classifier: Programming Language :: Python :: 3
Classifier: Programming Language :: Python :: 3.4
Classifier: Programming Language :: Python :: 3.5
Classifier: Programming Language :: Python :: 3.6
Classifier: Programming Language :: Python :: 3.7
Classifier: Programming Language :: Python :: 3.8
Classifier: Programming Language :: Python :: 3.9
